anymath/__init__.py
anymath-0.0.1.dist-info/LICENSE
anymath-0.0.1.dist-info/METADATA
anymath-0.0.1.dist-info/WHEEL
anymath-0.0.1.dist-info/top_level.txt
anymath-0.0.1.dist-info/RECORD
