Metadata-Version: 2.1
Name: anymath
Version: 0.0.1
Summary: tool for work witn any number systems
Home-page: https://github.com/Nikita-080/anymath-0.0.1
Author: Рябов Никита
Author-email: riabovnick080@yandex.ru
License: UNKNOWN
Platform: UNKNOWN
Classifier: Programming Language :: Python :: 3
Classifier: License :: OSI Approved :: MIT License
Classifier: Operating System :: OS Independent
Requires-Python: >=3.7
